LICENSE
README.md
pyproject.toml
setup.py
back_to_sit/__init__.py
back_to_sit/back_to_sit.py
back_to_sit.egg-info/PKG-INFO
back_to_sit.egg-info/SOURCES.txt
back_to_sit.egg-info/dependency_links.txt
back_to_sit.egg-info/requires.txt
back_to_sit.egg-info/top_level.txt