Metadata-Version: 2.1
Name: back-to-sit
Version: 0.0.7
Summary: Back to sit when the your code is ready
Author: Diego Machado
Author-email: dmachadovz@gmail.com
Keywords: python,telegram
License-File: LICENSE
